opengrad/__init__.py
opengrad/engine.py
opengrad/nn.py
opengrad-0.0.1.dist-info/METADATA
opengrad-0.0.1.dist-info/WHEEL
opengrad-0.0.1.dist-info/top_level.txt
opengrad-0.0.1.dist-info/RECORD
